planetscope_py/__init__.py
planetscope_py/_version.py
planetscope_py/adaptive_grid.py
planetscope_py/asset_manager.py
planetscope_py/auth.py
planetscope_py/config.py
planetscope_py/density_engine.py
planetscope_py/exceptions.py
planetscope_py/geopackage_manager.py
planetscope_py/geopackage_oneliners.py
planetscope_py/interactive_manager.py
planetscope_py/metadata.py
planetscope_py/optimizer.py
planetscope_py/preview_manager.py
planetscope_py/query.py
planetscope_py/rate_limiter.py
planetscope_py/temporal_analysis.py
planetscope_py/utils.py
planetscope_py/visualization.py
planetscope_py/workflows.py
planetscope_py-4.1.0.dist-info/licenses/LICENSE
tests/__init__.py
tests/conftest.py
tests/mock_planet_api.py
tests/test_asset_manager.py
tests/test_auth.py
tests/test_config.py
tests/test_exceptions.py
tests/test_geopackage_manager.py
tests/test_metadata.py
tests/test_query.py
tests/test_rate_limiter.py
tests/test_suite.py
tests/test_temporal_analysis.py
tests/test_utils.py
planetscope_py-4.1.0.dist-info/METADATA
planetscope_py-4.1.0.dist-info/WHEEL
planetscope_py-4.1.0.dist-info/entry_points.txt
planetscope_py-4.1.0.dist-info/top_level.txt
planetscope_py-4.1.0.dist-info/RECORD
