Metadata-Version: 2.4
Name: planetscope-py
Version: 4.1.0
Summary: Professional Python library for PlanetScope satellite imagery analysis with complete temporal analysis, spatial density analysis, and advanced data export capabilities
Home-page: https://github.com/Black-Lights/planetscope-py
Author: Ammar & Umayr
Author-email: mohammadammarmughees@gmail.com
Project-URL: Bug Reports, https://github.com/Black-Lights/planetscope-py/issues
Project-URL: Source, https://github.com/Black-Lights/planetscope-py
Project-URL: Documentation, https://github.com/Black-Lights/planetscope-py/wiki
Project-URL: Changelog, https://github.com/Black-Lights/planetscope-py/blob/main/CHANGELOG.md
Project-URL: PyPI, https://pypi.org/project/planetscope-py/
Keywords: satellite,imagery,planet,planetscope,geospatial,remote-sensing,earth-observation,gis,spatial-analysis,density-analysis,temporal-analysis,rasterization,vector-overlay,adaptive-grid,visualization,asset-management,geopackage,async-downloads,quota-monitoring,grid-based-analysis,coordinate-system-fixes,scene-footprints,metadata-processing,quality-assessment,metadata-fixes,json-serialization-fixes,scene-id-extraction,temporal-visualization,interactive-preview
Classifier: Development Status :: 5 - Production/Stable
Classifier: Intended Audience :: Developers
Classifier: Intended Audience :: Science/Research
Classifier: Topic :: Scientific/Engineering :: GIS
Classifier: Topic :: Scientific/Engineering :: Image Processing
Classifier: Topic :: Scientific/Engineering :: Visualization
Classifier: Topic :: Scientific/Engineering :: Atmospheric Science
Classifier: Topic :: Database
Classifier: License :: OSI Approved :: MIT License
Classifier: Programming Language :: Python :: 3
Classifier: Programming Language :: Python :: 3.10
Classifier: Programming Language :: Python :: 3.11
Classifier: Programming Language :: Python :: 3.12
Classifier: Operating System :: OS Independent
Classifier: Framework :: AsyncIO
Classifier: Environment :: Console
Classifier: Natural Language :: English
Requires-Python: >=3.10
License-File: LICENSE
Requires-Dist: requests>=2.32.4
Requires-Dist: shapely>=2.1.0
Requires-Dist: pyproj>=3.7.1
Requires-Dist: numpy>=2.2.0
Requires-Dist: pandas>=2.2.3
Requires-Dist: python-dateutil>=2.9.0
Requires-Dist: orjson>=3.10.0
Requires-Dist: xarray>=2024.02.0
Requires-Dist: aiohttp>=3.8.0
Requires-Dist: geopandas>=1.0.1
Requires-Dist: fiona>=1.9.0
Requires-Dist: rasterio>=1.4.3
Requires-Dist: scipy>=1.13.0
Requires-Dist: matplotlib>=3.10.0
Requires-Dist: contextily>=1.6.2
Requires-Dist: folium>=0.19.1
Requires-Dist: seaborn>=0.12.2
Provides-Extra: dev
Requires-Dist: pytest>=8.3.4; extra == "dev"
Requires-Dist: pytest-cov>=6.0.0; extra == "dev"
Requires-Dist: pytest-mock>=3.14.0; extra == "dev"
Requires-Dist: pytest-xdist>=3.6.0; extra == "dev"
Requires-Dist: pytest-asyncio>=0.24.0; extra == "dev"
Requires-Dist: black>=24.12.0; extra == "dev"
Requires-Dist: flake8>=7.2.0; extra == "dev"
Requires-Dist: flake8-bugbear>=24.12.12; extra == "dev"
Requires-Dist: flake8-docstrings>=1.7.0; extra == "dev"
Requires-Dist: mypy>=1.13.0; extra == "dev"
Requires-Dist: types-requests>=2.32.0.20241217; extra == "dev"
Requires-Dist: pre-commit>=4.0.1; extra == "dev"
Requires-Dist: ruff>=0.8.1; extra == "dev"
Requires-Dist: bandit>=1.8.0; extra == "dev"
Requires-Dist: build>=1.2.2; extra == "dev"
Requires-Dist: twine>=6.0.1; extra == "dev"
Requires-Dist: wheel>=0.45.1; extra == "dev"
Provides-Extra: docs
Requires-Dist: sphinx>=8.1.3; extra == "docs"
Requires-Dist: sphinx-rtd-theme>=3.0.2; extra == "docs"
Requires-Dist: myst-parser>=4.0.0; extra == "docs"
Provides-Extra: jupyter
Requires-Dist: jupyter>=1.1.1; extra == "jupyter"
Requires-Dist: ipywidgets>=8.1.5; extra == "jupyter"
Requires-Dist: notebook>=7.3.1; extra == "jupyter"
Provides-Extra: spatial
Requires-Dist: plotly>=5.24.1; extra == "spatial"
Provides-Extra: temporal
Requires-Dist: plotly>=5.24.1; extra == "temporal"
Provides-Extra: asset
Requires-Dist: tqdm>=4.66.0; extra == "asset"
Provides-Extra: geopackage
Requires-Dist: sqlite3; extra == "geopackage"
Provides-Extra: interactive
Requires-Dist: ipywidgets>=8.1.5; extra == "interactive"
Requires-Dist: jupyter>=1.1.1; extra == "interactive"
Requires-Dist: notebook>=7.3.1; extra == "interactive"
Provides-Extra: viz
Requires-Dist: plotly>=5.24.1; extra == "viz"
Requires-Dist: bokeh>=3.0.0; extra == "viz"
Provides-Extra: performance
Requires-Dist: line-profiler>=4.2.0; extra == "performance"
Requires-Dist: memory-profiler>=0.61.0; extra == "performance"
Provides-Extra: all
Requires-Dist: pytest>=8.3.4; extra == "all"
Requires-Dist: pytest-cov>=6.0.0; extra == "all"
Requires-Dist: pytest-mock>=3.14.0; extra == "all"
Requires-Dist: pytest-asyncio>=0.24.0; extra == "all"
Requires-Dist: black>=24.12.0; extra == "all"
Requires-Dist: flake8>=7.2.0; extra == "all"
Requires-Dist: mypy>=1.13.0; extra == "all"
Requires-Dist: pre-commit>=4.0.1; extra == "all"
Requires-Dist: sphinx>=8.1.3; extra == "all"
Requires-Dist: sphinx-rtd-theme>=3.0.2; extra == "all"
Requires-Dist: jupyter>=1.1.1; extra == "all"
Requires-Dist: ipywidgets>=8.1.5; extra == "all"
Requires-Dist: notebook>=7.3.1; extra == "all"
Requires-Dist: plotly>=5.24.1; extra == "all"
Requires-Dist: bokeh>=3.0.0; extra == "all"
Requires-Dist: tqdm>=4.66.0; extra == "all"
Dynamic: author
Dynamic: author-email
Dynamic: classifier
Dynamic: description
Dynamic: description-content-type
Dynamic: home-page
Dynamic: keywords
Dynamic: license-file
Dynamic: project-url
Dynamic: provides-extra
Dynamic: requires-dist
Dynamic: requires-python
Dynamic: summary
